deep_sort_reid/DeepSortReid.py
deep_sort_reid/__init__.py
deep_sort_reid/constants/__init__.py
deep_sort_reid/constants/tracker.py
deep_sort_reid/enums/__init__.py
deep_sort_reid/enums/tracker.py
deep_sort_reid/metric/GatedMetric.py
deep_sort_reid/metric/IouMetric.py
deep_sort_reid/metric/Metric.py
deep_sort_reid/metric/__init__.py
deep_sort_reid/models/__init__.py
deep_sort_reid/models/motion/KalmanFilter.py
deep_sort_reid/models/motion/__init__.py
deep_sort_reid/storage/CacheStorage.py
deep_sort_reid/storage/__init__.py
deep_sort_reid/tracker/Track.py
deep_sort_reid/tracker/Tracker.py
deep_sort_reid/tracker/__init__.py
deep_sort_reid/types/__init__.py
deep_sort_reid/types/coords.py
deep_sort_reid/types/detection.py
deep_sort_reid/types/metric.py
deep_sort_reid/types/storage.py
deep_sort_reid/types/tracker.py
deep_sort_reid/utils/__init__.py
deep_sort_reid/utils/box_methods.py
deep_sort_reid/utils/detect_objects.py
deep_sort_reid/utils/extract_features.py
deep_sort_reid/utils/linear_assignment.py
deep_sort_reid/utils/misc.py
deep_sort_reid/utils/suppression.py
deep_sort_reid-0.1.7.dist-info/LICENSE
deep_sort_reid-0.1.7.dist-info/METADATA
deep_sort_reid-0.1.7.dist-info/WHEEL
deep_sort_reid-0.1.7.dist-info/top_level.txt
deep_sort_reid-0.1.7.dist-info/RECORD
