Metadata-Version: 2.1
Name: deep_sort_reid
Version: 0.1.7
Summary: A re-mastered version of the original Deep Sort implementation, with added functionalities such as re-identification.
Home-page: https://github.com/cajmorgan/deep_sort_reid
Author: Caj Morgan
Author-email: caj@maiosolutions.com
License: GPL-3.0
Platform: UNKNOWN
Requires-Python: >=3.10.0
License-File: LICENSE
